nba_stats/__init__.py
nba_stats/stats.py
tests/__init__.py
tests/test_stats.py
nba_analytica-0.1.0.dist-info/METADATA
nba_analytica-0.1.0.dist-info/WHEEL
nba_analytica-0.1.0.dist-info/top_level.txt
nba_analytica-0.1.0.dist-info/RECORD
