Metadata-Version: 2.1
Name: nba_analytica
Version: 0.1.0
Summary: A package to fetch NBA player stats.
Home-page: https://github.com/Adamlip1334/nba-stats
Author: Adam Lipson
Author-email: lipson.adam13@gmail.com
License: MIT
Requires-Dist: requests
